Naftawayh-0.4.dist-info/DESCRIPTION.rst
Naftawayh-0.4.dist-info/METADATA
Naftawayh-0.4.dist-info/RECORD
Naftawayh-0.4.dist-info/WHEEL
Naftawayh-0.4.dist-info/metadata.json
Naftawayh-0.4.dist-info/top_level.txt
naftawayh/__init__.py
naftawayh/affix_const.py
naftawayh/ar_ctype.py
naftawayh/ar_stopwords.py
naftawayh/ar_stowords.py
naftawayh/arabic_const.py
naftawayh/create_verbstamp.py
naftawayh/specialwords.py
naftawayh/stopwords.py
naftawayh/verb_dictionary.py
naftawayh/verb_stamp.py
naftawayh/wordtag.py
naftawayh/wordtag_const.py
