Metadata-Version: 2.1
Name: Naftawayh
Version: 0.4
Summary: Naftawayh: Arabic word tagger
Home-page: http://naftawayh.sourceforge.net/
Author: Taha Zerrouki
Author-email: taha.zerrouki@gmail.com
License: GPL
Platform: UNKNOWN
Classifier: Development Status :: 5 - Production/Stable
Classifier: Intended Audience :: End Users/Desktop
Classifier: Operating System :: OS Independent
Classifier: Programming Language :: Python
Requires-Dist: pyarabic
Requires-Dist: tashaphyne
